ftools/__init__.py
ftools/cli.py
ftools/helper.py
ftools/version.py
ftools/commands/__init__.py
ftools/commands/cmd_css.py
ftools/commands/cmd_extract.py
camp_ftools-0.0.1.dist-info/entry_points.txt
camp_ftools-0.0.1.dist-info/WHEEL
camp_ftools-0.0.1.dist-info/METADATA
camp_ftools-0.0.1.dist-info/RECORD
