Metadata-Version: 2.1
Name: camp_ftools
Version: 0.0.1
Summary: 营地字体处理工具库
Keywords: font,font-tools
Author-email: bobi <bobiloveali@gmail.com>
Requires-Python: >=3.8
Classifier: Programming Language :: Python :: 3
Classifier: License :: OSI Approved :: MIT License
Classifier: Operating System :: OS Independent
Classifier: Environment :: Console
Requires-Dist: click>=8.1
Requires-Dist: fonttools
Requires-Dist: brotli
